Metadata-Version: 1.0
Name: asreq
Version: 0.0.3
Summary: Faster lib for async socket requests
Home-page: UNKNOWN
Author: UNKNOWN
Author-email: xazkerboy@gmail.com
License: UNKNOWN
Platform: UNKNOWN
